jyp-0.1.3.data/scripts/jyp
src/twice/__init__.py
src/twice/fetching.py
src/twice/processing.py
src/twice/sending.py
jyp-0.1.3.dist-info/LICENSE
jyp-0.1.3.dist-info/METADATA
jyp-0.1.3.dist-info/WHEEL
jyp-0.1.3.dist-info/top_level.txt
jyp-0.1.3.dist-info/RECORD
