Metadata-Version: 2.1
Name: jyp
Version: 0.1.3
Summary: Pocket converter for Korean to Canadian currency
Home-page: https://github.com/MDAddario/jyp
Author: Michael Lindner-D'Addario
Author-email: michael.lindner.daddario@gmail.com
License: UNKNOWN
Platform: UNKNOWN
Classifier: Programming Language :: Python :: 3
Classifier: License :: OSI Approved :: MIT License
Classifier: Operating System :: OS Independent
Requires-Python: >=3.6
Requires-Dist: numpy (>=1.20.3)
Requires-Dist: pandas
